<?xml version="1.0" encoding="gbk"?>
	<annotation>
		<folder>cartoon</folder>
		<filename>003053.jpg</filename>
		<path>g:</path>
		<source>
			<database>Unknown</database>
		</source>
		<size>
			<width>896</width>
			<height>504</height>
			<depth>3</depth>
		</size>
		<segmented>0</segmented>
		<object>
			<name>0</name>
			<pose>Unspecified</pose>
			<truncated>0</truncated>
			<difficult>0</difficult>
			<bndbox>
				<xmin>385</xmin>
				<ymin>161</ymin>
				<xmax>451</xmax>
				<ymax>239</ymax>
			</bndbox>
		</object>
		<object>
			<name>0</name>
			<pose>Unspecified</pose>
			<truncated>0</truncated>
			<difficult>0</difficult>
			<bndbox>
				<xmin>242</xmin>
				<ymin>143</ymin>
				<xmax>299</xmax>
				<ymax>206</ymax>
			</bndbox>
		</object>
		<object>
			<name>0</name>
			<pose>Unspecified</pose>
			<truncated>0</truncated>
			<difficult>0</difficult>
			<bndbox>
				<xmin>148</xmin>
				<ymin>153</ymin>
				<xmax>211</xmax>
				<ymax>241</ymax>
			</bndbox>
		</object>
	</annotation>
