<?xml version="1.0" encoding="gbk"?>
	<annotation>
		<folder>cartoon</folder>
		<filename>004252.jpg</filename>
		<path>g:</path>
		<source>
			<database>Unknown</database>
		</source>
		<size>
			<width>850</width>
			<height>477</height>
			<depth>3</depth>
		</size>
		<segmented>0</segmented>
		<object>
			<name>0</name>
			<pose>Unspecified</pose>
			<truncated>0</truncated>
			<difficult>0</difficult>
			<bndbox>
				<xmin>49</xmin>
				<ymin>2</ymin>
				<xmax>232</xmax>
				<ymax>108</ymax>
			</bndbox>
		</object>
		<object>
			<name>0</name>
			<pose>Unspecified</pose>
			<truncated>0</truncated>
			<difficult>0</difficult>
			<bndbox>
				<xmin>76</xmin>
				<ymin>412</ymin>
				<xmax>184</xmax>
				<ymax>479</ymax>
			</bndbox>
		</object>
	</annotation>
