<?xml version="1.0" encoding="gbk"?>
	<annotation>
		<folder>cartoon</folder>
		<filename>004434.jpg</filename>
		<path>g:</path>
		<source>
			<database>Unknown</database>
		</source>
		<size>
			<width>5472</width>
			<height>3648</height>
			<depth>3</depth>
		</size>
		<segmented>0</segmented>
		<object>
			<name>0</name>
			<pose>Unspecified</pose>
			<truncated>0</truncated>
			<difficult>0</difficult>
			<bndbox>
				<xmin>2</xmin>
				<ymin>242</ymin>
				<xmax>68</xmax>
				<ymax>371</ymax>
			</bndbox>
		</object>
		<object>
			<name>0</name>
			<pose>Unspecified</pose>
			<truncated>0</truncated>
			<difficult>0</difficult>
			<bndbox>
				<xmin>190</xmin>
				<ymin>262</ymin>
				<xmax>339</xmax>
				<ymax>379</ymax>
			</bndbox>
		</object>
		<object>
			<name>0</name>
			<pose>Unspecified</pose>
			<truncated>0</truncated>
			<difficult>0</difficult>
			<bndbox>
				<xmin>474</xmin>
				<ymin>253</ymin>
				<xmax>620</xmax>
				<ymax>376</ymax>
			</bndbox>
		</object>
		<object>
			<name>0</name>
			<pose>Unspecified</pose>
			<truncated>0</truncated>
			<difficult>0</difficult>
			<bndbox>
				<xmin>562</xmin>
				<ymin>379</ymin>
				<xmax>589</xmax>
				<ymax>402</ymax>
			</bndbox>
		</object>
		<object>
			<name>0</name>
			<pose>Unspecified</pose>
			<truncated>0</truncated>
			<difficult>0</difficult>
			<bndbox>
				<xmin>591</xmin>
				<ymin>379</ymin>
				<xmax>617</xmax>
				<ymax>403</ymax>
			</bndbox>
		</object>
	</annotation>
