<?xml version="1.0" encoding="gbk"?>
	<annotation>
		<folder>cartoon</folder>
		<filename>004540.jpg</filename>
		<path>g:</path>
		<source>
			<database>Unknown</database>
		</source>
		<size>
			<width>896</width>
			<height>504</height>
			<depth>3</depth>
		</size>
		<segmented>0</segmented>
		<object>
			<name>0</name>
			<pose>Unspecified</pose>
			<truncated>0</truncated>
			<difficult>0</difficult>
			<bndbox>
				<xmin>314</xmin>
				<ymin>11</ymin>
				<xmax>352</xmax>
				<ymax>43</ymax>
			</bndbox>
		</object>
		<object>
			<name>0</name>
			<pose>Unspecified</pose>
			<truncated>0</truncated>
			<difficult>0</difficult>
			<bndbox>
				<xmin>215</xmin>
				<ymin>303</ymin>
				<xmax>266</xmax>
				<ymax>373</ymax>
			</bndbox>
		</object>
		<object>
			<name>0</name>
			<pose>Unspecified</pose>
			<truncated>0</truncated>
			<difficult>0</difficult>
			<bndbox>
				<xmin>140</xmin>
				<ymin>303</ymin>
				<xmax>197</xmax>
				<ymax>362</ymax>
			</bndbox>
		</object>
		<object>
			<name>0</name>
			<pose>Unspecified</pose>
			<truncated>0</truncated>
			<difficult>0</difficult>
			<bndbox>
				<xmin>188</xmin>
				<ymin>367</ymin>
				<xmax>263</xmax>
				<ymax>433</ymax>
			</bndbox>
		</object>
		<object>
			<name>0</name>
			<pose>Unspecified</pose>
			<truncated>0</truncated>
			<difficult>0</difficult>
			<bndbox>
				<xmin>141</xmin>
				<ymin>407</ymin>
				<xmax>186</xmax>
				<ymax>469</ymax>
			</bndbox>
		</object>
		<object>
			<name>0</name>
			<pose>Unspecified</pose>
			<truncated>0</truncated>
			<difficult>0</difficult>
			<bndbox>
				<xmin>332</xmin>
				<ymin>453</ymin>
				<xmax>348</xmax>
				<ymax>471</ymax>
			</bndbox>
		</object>
		<object>
			<name>0</name>
			<pose>Unspecified</pose>
			<truncated>0</truncated>
			<difficult>0</difficult>
			<bndbox>
				<xmin>211</xmin>
				<ymin>475</ymin>
				<xmax>286</xmax>
				<ymax>557</ymax>
			</bndbox>
		</object>
		<object>
			<name>0</name>
			<pose>Unspecified</pose>
			<truncated>0</truncated>
			<difficult>0</difficult>
			<bndbox>
				<xmin>155</xmin>
				<ymin>531</ymin>
				<xmax>200</xmax>
				<ymax>584</ymax>
			</bndbox>
		</object>
	</annotation>
